automation_logging/__init__.py
automation_logging-1.0.5.dist-info/licenses/LICENSE
automation_logging-1.0.5.dist-info/METADATA
automation_logging-1.0.5.dist-info/WHEEL
automation_logging-1.0.5.dist-info/top_level.txt
automation_logging-1.0.5.dist-info/RECORD
