Metadata-Version: 2.4
Name: automation-logging
Version: 1.0.5
Summary: Logging for automation, offering thread-safety, log cleanup and screenshot support.
Home-page: https://github.com/VBenevides/automation-logging
Author: Vinicius Benevides
Author-email: massaki1999@gmail.com
License: MIT
License-File: LICENSE
Provides-Extra: selenium
Requires-Dist: selenium; extra == "selenium"
Provides-Extra: pyautogui
Requires-Dist: pyautogui; extra == "pyautogui"
Requires-Dist: pyscreeze; extra == "pyautogui"
Requires-Dist: pillow; extra == "pyautogui"
Provides-Extra: all
Requires-Dist: selenium; extra == "all"
Requires-Dist: pyautogui; extra == "all"
Requires-Dist: pyscreeze; extra == "all"
Requires-Dist: pillow; extra == "all"
Dynamic: author
Dynamic: author-email
Dynamic: description
Dynamic: description-content-type
Dynamic: home-page
Dynamic: license
Dynamic: license-file
Dynamic: provides-extra
Dynamic: summary
